kkmeans/__init__.py
kkmeans/init_clusters.py
kkmeans/kernel_functions.py
kkmeans/kkmeans.py
python_kkmeans-0.1.0.dist-info/LICENSE.txt
python_kkmeans-0.1.0.dist-info/METADATA
python_kkmeans-0.1.0.dist-info/WHEEL
python_kkmeans-0.1.0.dist-info/top_level.txt
python_kkmeans-0.1.0.dist-info/RECORD
