Metadata-Version: 2.1
Name: python-kkmeans
Version: 0.1.0
Summary: An implementation of the Kernel k-means algorithm for a bachelorthesis.
Author: Johannes Oster
License-File: LICENSE.txt
